{"type": "Feature", "id": 12523654, "geometry": {"type": "Point", "coordinates": [-61.016701, 5.81667]}, "properties": {"woe:id": 12523654, "woe:parent_id": 376814, "woe:name": "Paruima Airport", "woe:placetype": 14, "woe:placetype_name": "Airport", "woe:lang": "ENG", "iso:country": "GY", "meta:provider": ["geoplanet:7.3.1", "geoplanet:7.3.2", "geoplanet:7.4.0", "geoplanet:7.4.1", "geoplanet:7.5.1", "geoplanet:7.5.2", "geoplanet:7.6.0", "geoplanet:7.8.1", "geoplanet:7.9.0", "geoplanet:7.10.0", "geoplanet:8.0.0", "woeplanet:8.0.0"], "meta:indexed": "2020-08-20T20:25:55.236646", "woe:alias_ENG_V": ["PRR Airport", "PRR"], "meta:updated": "2020-10-14T11:05:10.364886", "woe:hierarchy": {"continent": 24865673, "country": 23424836, "town": 0, "planet": 1, "county": 0, "suburb": 0, "state": 2345604, "region": 0, "localadmin": 0}, "woe:timezone_id": 28350763, "woe:hash": "d9h95dbuxcfh", "woe:centroid": [-61.016701, 5.81667], "geom:latitude": 5.81667, "geom:longitude": -61.016701, "geom:hash": "d9h95dbuxcfh", "woe:latitude": 5.81667, "geom:centroid": [-61.016701, 5.81667], "woe:longitude": -61.016701, "woe:repo": "woeplanet-airport-gy", "geom:area": 0.0, "woe:scale": 19}}